expediagroup/sdk/fraudpreventionv2/__init__.py
expediagroup/sdk/fraudpreventionv2/client.py
expediagroup/sdk/fraudpreventionv2/model.py
expediagroup_fraudpreventionv2_sdk-4.0.0.dist-info/METADATA
expediagroup_fraudpreventionv2_sdk-4.0.0.dist-info/WHEEL
expediagroup_fraudpreventionv2_sdk-4.0.0.dist-info/top_level.txt
expediagroup_fraudpreventionv2_sdk-4.0.0.dist-info/RECORD
