Metadata-Version: 2.1
Name: expediagroup-fraudpreventionv2-sdk
Version: 4.0.0
Summary: Expedia Group Fraud Prevention V2 SDK for Python
Home-page: https://github.com/ExpediaGroup/expediagroup-python-sdk
Author: Expedia Group
Author-email: oss@expediagroup.com
License: Apache License, Version 2.0
Classifier: Development Status :: 3 - Alpha
Classifier: Programming Language :: Python
Classifier: Programming Language :: Python :: 3 :: Only
Classifier: Programming Language :: Python :: 3
Classifier: Programming Language :: Python :: 3.8
Classifier: Programming Language :: Python :: 3.9
Classifier: Programming Language :: Python :: 3.10
Classifier: Programming Language :: Python :: 3.11
Classifier: License :: OSI Approved :: MIT License
Requires-Python: >=3.8
Requires-Dist: uri
Requires-Dist: furl
Requires-Dist: expediagroup-sdk-python-core
Requires-Dist: pydantic
Requires-Dist: pydantic[email]
Requires-Dist: email-validator
